[
  {
    "english": "to go",
    "ojibwe_lemma": "",
    "stem": "",
    "class": "",
    "category": "movement",
    "source": "Rama dictionary",
    "source_page": "",
    "notes": "",
    "confidence": "unentered"
  },
  {
    "english": "to come",
    "ojibwe_lemma": "",
    "stem": "",
    "class": "",
    "category": "movement",
    "source": "Rama dictionary",
    "source_page": "",
    "notes": "",
    "confidence": "unentered"
  },
  {
    "english": "to eat",
    "ojibwe_lemma": "",
    "stem": "",
    "class": "",
    "category": "home",
    "source": "Rama dictionary",
    "source_page": "",
    "notes": "",
    "confidence": "unentered"
  },
  {
    "english": "Run",
    "ojibwe_lemma": "",
    "stem": "",
    "class": "",
    "category": "home",
    "source": "Rama dictionary",
    "source_page": "",
    "notes": "",
    "confidence": "dictionary-based"
  }
]